ord/__init__.py
ord/client.py
ord/models.py
ord/urls.py
ordeal-0.0.11.dist-info/LICENSE
ordeal-0.0.11.dist-info/METADATA
ordeal-0.0.11.dist-info/WHEEL
ordeal-0.0.11.dist-info/RECORD
