Metadata-Version: 2.1
Name: ordeal
Version: 0.0.11
Summary: bitcoin jpegs
Author: Sam Barnes
Author-email: sam.barnes@opensea.io
Requires-Python: >=3.10,<4.0
Classifier: Programming Language :: Python :: 3
Classifier: Programming Language :: Python :: 3.10
Classifier: Programming Language :: Python :: 3.11
Requires-Dist: beautifulsoup4 (>=4.10.0,<5.0.0)
Requires-Dist: httpx (>=0.23.3,<0.24.0)
Requires-Dist: pydantic (>=1.10.0,<2.0.0)
